jam/__init__.py
jam/choice.py
jam/misc.py
jam/pitch.py
jam/plot.py
jam/shuffle.py
jam/soxsynth.py
jam-0.0.4.dist-info/DESCRIPTION.rst
jam-0.0.4.dist-info/METADATA
jam-0.0.4.dist-info/metadata.json
jam-0.0.4.dist-info/pbr.json
jam-0.0.4.dist-info/RECORD
jam-0.0.4.dist-info/top_level.txt
jam-0.0.4.dist-info/WHEEL
