Metadata-Version: 2.0
Name: jam
Version: 0.0.4
Summary: Jonathan's assorted music utilities
Home-page: https://github.com/jonathanmarmor/jam
Author: Jonathan Marmor
Author-email: jmarmor@gmail.com
License: GPL
Keywords: music
Platform: UNKNOWN
Classifier: License :: OSI Approved :: GNU General Public License (GPL)
Classifier: Programming Language :: Python
Classifier: Development Status :: 3 - Alpha
Classifier: Intended Audience :: Developers
Requires-Dist: matplotlib
